ai_getter/__init__.py
ai_getter/main.py
ai_getter/save.py
ai_getter-0.0.2.dist-info/METADATA
ai_getter-0.0.2.dist-info/WHEEL
ai_getter-0.0.2.dist-info/entry_points.txt
ai_getter-0.0.2.dist-info/top_level.txt
ai_getter-0.0.2.dist-info/RECORD
