Metadata-Version: 2.1
Name: ai-getter
Version: 0.0.2
Summary: A CLI for publishing sites to Netlify and assigning custom domains to them.
Home-page: https://github.com/zevaverbach/ai_getter
Author: Zev Averbach
Author-email: zev@averba.ch
License: MIT
Classifier: Development Status :: 3 - Alpha
Classifier: Intended Audience :: Developers
Classifier: License :: OSI Approved :: MIT License
Classifier: Programming Language :: Python :: 3
Classifier: Programming Language :: Python :: 3.10
Classifier: Programming Language :: Python :: 3.11
Requires-Python: >=3.10
Requires-Dist: requests
Requires-Dist: openai
Requires-Dist: pyperclip
Requires-Dist: trans
Requires-Dist: boto3
